[{"id":1,"breed_name":"Golden Retriever","dog_name":"Devy","weight":11.93},
{"id":2,"breed_name":"German Shepherd","dog_name":"Kleon","weight":35.35},
{"id":3,"breed_name":"Poodle","dog_name":"Etta","weight":16.7},
{"id":4,"breed_name":"Beagle","dog_name":"Stefania","weight":46.92},
{"id":5,"breed_name":"Beagle","dog_name":"Babbette","weight":29.54},
{"id":6,"breed_name":"Beagle","dog_name":"Gauthier","weight":33.7},
{"id":7,"breed_name":"Rottweiler","dog_name":"Leda","weight":28.86},
{"id":8,"breed_name":"German Shepherd","dog_name":"Zarla","weight":32.13},
{"id":9,"breed_name":"French Bulldog","dog_name":"Carlene","weight":30.19},
{"id":10,"breed_name":"German Shepherd","dog_name":"Richie","weight":25.14}]